hello.v
`timescale 1ns / 1ps
module hello(
    input clk,
    input reset,
    input [1:0] Hour_in1,
    input [3:0] Hour_in0,
    input [3:0] Minute_in1,
    input [3:0] Minute_in0,
    input Load_time,
    input Load_alarm,
    input Stop_alarm,
    input Al_On,
    output reg Alarm,
    output [1:0] Hour_out1,
    output [3:0] Hour_out0,
    output [3:0] Minute_out1,
    output [3:0] Minute_out0,
    output [3:0] Second_out1,
    output [3:0] Second_out0
);

reg [5:0] temp_hour, temp_minute, temp_second;
reg [1:0] c_hour1, a_hour1;
reg [3:0] c_hour0, a_hour0, c_min1, a_min1, c_min0, a_min0, c_sec1, a_sec1, c_sec0, a_sec0;

// Function to get tens digit
function [3:0] mod_10(input [5:0] number);
    mod_10 = number / 10;
endfunction

// Time and alarm loading / updating
always @(posedge clk or posedge reset) begin
    if (reset) begin
        {a_hour1, a_hour0, a_min1, a_min0, a_sec1, a_sec0} <= 0;
        temp_hour <= Hour_in1 * 10 + Hour_in0;
        temp_minute <= Minute_in1 * 10 + Minute_in0;
        temp_second <= 0;
    end else begin
        if (Load_alarm) begin
            {a_hour1, a_hour0, a_min1, a_min0, a_sec1, a_sec0} <= {Hour_in1, Hour_in0, Minute_in1, Minute_in0, 4'b0, 4'b0};
        end else if (Load_time) begin
            temp_hour <= Hour_in1 * 10 + Hour_in0;
            temp_minute <= Minute_in1 * 10 + Minute_in0;
            temp_second <= 0;
        end else begin
            temp_second <= temp_second + 1;
            if (temp_second >= 60) begin
                temp_second <= 0;
                temp_minute <= temp_minute + 1;
                if (temp_minute >= 60) begin
                    temp_minute <= 0;
                    temp_hour <= temp_hour + 1;
                    if (temp_hour >= 24) temp_hour <= 0;
                end
            end
        end
    end
end

// BCD Conversion
always @(*) begin
    c_hour1 = temp_hour / 10;
    c_hour0 = temp_hour % 10;
    c_min1 = temp_minute / 10;
    c_min0 = temp_minute % 10;
    c_sec1 = temp_second / 10;
    c_sec0 = temp_second % 10;
end

// Alarm logic
always @(posedge clk or posedge reset) begin
    if (reset)
        Alarm <= 0;
    else begin
        if ({a_hour1, a_hour0, a_min1, a_min0, a_sec1, a_sec0} == {c_hour1, c_hour0, c_min1, c_min0, c_sec1, c_sec0})
            if (Al_On) Alarm <= 1;
        if (Stop_alarm) Alarm <= 0;
    end
end

assign Hour_out1 = c_hour1;
assign Hour_out0 = c_hour0;
assign Minute_out1 = c_min1;
assign Minute_out0 = c_min0;
assign Second_out1 = c_sec1;
assign Second_out0 = c_sec0;

endmodule

hello_tb.v
`include "hello.v"

module hello_tb;

reg reset, clk;
reg [1:0] Hour_in1;
reg [3:0] Hour_in0, Minute_in1, Minute_in0;
reg Load_time, Load_alarm, Stop_alarm, Al_On;

wire Alarm;
wire [1:0] Hour_out1;
wire [3:0] Hour_out0, Minute_out1, Minute_out0, Second_out1, Second_out0;

// Instantiate DUT
hello uut (
    .reset(reset),
    .clk(clk),
    .Hour_in1(Hour_in1),
    .Hour_in0(Hour_in0),
    .Minute_in1(Minute_in1),
    .Minute_in0(Minute_in0),
    .Load_time(Load_time),
    .Load_alarm(Load_alarm),
    .Stop_alarm(Stop_alarm),
    .Al_On(Al_On),
    .Alarm(Alarm),
    .Hour_out1(Hour_out1),
    .Hour_out0(Hour_out0),
    .Minute_out1(Minute_out1),
    .Minute_out0(Minute_out0),
    .Second_out1(Second_out1),
    .Second_out0(Second_out0)
);

// Clock generation
initial clk = 0;
always #5 clk = ~clk;  // Fast clock for simulation

// Monitor output
always @(posedge clk) begin
    $display("Time: %0d%0d:%0d%0d:%0d%0d | Alarm: %b", 
        Hour_out1, Hour_out0, Minute_out1, Minute_out0, Second_out1, Second_out0, Alarm);
end

// Stimulus
initial begin
    $dumpfile("hello.vcd");
    $dumpvars(0, hello_tb);

    // Initialize
    reset = 1; Load_time = 0; Load_alarm = 0; Stop_alarm = 0; Al_On = 0;
    Hour_in1 = 2; Hour_in0 = 3; // Start Time = 23
    Minute_in1 = 5; Minute_in0 = 8; // 58 minutes
    #20;

    reset = 0; Load_time = 1; #10; Load_time = 0;

    // Set alarm at 23:59:02
    #10;
    Hour_in1 = 2; Hour_in0 = 3;
    Minute_in1 = 5; Minute_in0 = 9;
    Load_alarm = 1; Al_On = 1; 
    #10; Load_alarm = 0;

    // Wait until alarm triggers
    wait (Alarm == 1);
    $display(">>> Alarm Triggered at %0d%0d:%0d%0d:%0d%0d", 
        Hour_out1, Hour_out0, Minute_out1, Minute_out0, Second_out1, Second_out0);

    #20; Stop_alarm = 1;
    #10; Stop_alarm = 0;

    #50;
    $finish;
end

endmodule

hello.vcd
$date
	Wed Jul 16 16:23:45 2025
$end
$version
	Icarus Verilog
$end
$timescale
	1ps
$end
$scope module hello_tb $end
$var wire 1 ! Alarm $end
$var wire 4 " Hour_out0 [3:0] $end
$var wire 2 # Hour_out1 [1:0] $end
$var wire 4 $ Minute_out0 [3:0] $end
$var wire 4 % Minute_out1 [3:0] $end
$var wire 4 & Second_out0 [3:0] $end
$var wire 4 ' Second_out1 [3:0] $end
$var reg 1 ( Al_On $end
$var reg 4 ) Hour_in0 [3:0] $end
$var reg 2 * Hour_in1 [1:0] $end
$var reg 1 + Load_alarm $end
$var reg 1 , Load_time $end
$var reg 4 - Minute_in0 [3:0] $end
$var reg 4 . Minute_in1 [3:0] $end
$var reg 1 / Stop_alarm $end
$var reg 1 0 clk $end
$var reg 1 1 reset $end
$scope module uut $end
$var wire 1 2 Al_On $end
$var wire 4 3 Hour_in0 [3:0] $end
$var wire 2 4 Hour_in1 [1:0] $end
$var wire 4 5 Hour_out0 [3:0] $end
$var wire 2 6 Hour_out1 [1:0] $end
$var wire 1 7 Load_alarm $end
$var wire 1 8 Load_time $end
$var wire 4 9 Minute_in0 [3:0] $end
$var wire 4 : Minute_in1 [3:0] $end
$var wire 4 ; Minute_out0 [3:0] $end
$var wire 4 < Minute_out1 [3:0] $end
$var wire 4 = Second_out0 [3:0] $end
$var wire 4 > Second_out1 [3:0] $end
$var wire 1 ? Stop_alarm $end
$var wire 1 @ clk $end
$var wire 1 A reset $end
$var reg 1 B Alarm $end
$var reg 4 C a_hour0 [3:0] $end
$var reg 2 D a_hour1 [1:0] $end
$var reg 4 E a_min0 [3:0] $end
$var reg 4 F a_min1 [3:0] $end
$var reg 4 G a_sec0 [3:0] $end
$var reg 4 H a_sec1 [3:0] $end
$var reg 4 I c_hour0 [3:0] $end
$var reg 2 J c_hour1 [1:0] $end
$var reg 4 K c_min0 [3:0] $end
$var reg 4 L c_min1 [3:0] $end
$var reg 4 M c_sec0 [3:0] $end
$var reg 4 N c_sec1 [3:0] $end
$var reg 6 O temp_hour [5:0] $end
$var reg 6 P temp_minute [5:0] $end
$var reg 6 Q temp_second [5:0] $end
$scope function mod_10 $end
$var reg 4 R mod_10 [3:0] $end
$var reg 6 S number [5:0] $end
$upscope $end
$upscope $end
$upscope $end
$enddefinitions $end
#0
$dumpvars
bx S
bx R
b0 Q
b111010 P
b10111 O
b0 N
b0 M
b101 L
b1000 K
b10 J
b11 I
b0 H
b0 G
b0 F
b0 E
b0 D
b0 C
0B
1A
0@
0?
b0 >
b0 =
b101 <
b1000 ;
b101 :
b1000 9
08
07
b10 6
b11 5
b10 4
b11 3
02
11
00
0/
b101 .
b1000 -
0,
0+
b10 *
b11 )
0(
b0 '
b0 &
b101 %
b1000 $
b10 #
b11 "
0!
$end
#5000
10
1@
#10000
00
0@
#15000
10
1@
#20000
00
0@
1,
18
01
0A
#25000
10
1@
#30000
00
0@
0,
08
#35000
b1 M
b1 &
b1 =
b1 Q
10
1@
#40000
00
0@
1(
12
1+
17
b1001 -
b1001 9
#45000
b10 D
b11 C
b101 F
b1001 E
10
1@
#50000
00
0@
0+
07
#55000
b10 M
b10 &
b10 =
b10 Q
10
1@
#60000
00
0@
#65000
b11 M
b11 &
b11 =
b11 Q
10
1@
#70000
00
0@
#75000
b100 M
b100 &
b100 =
b100 Q
10
1@
#80000
00
0@
#85000
b101 M
b101 &
b101 =
b101 Q
10
1@
#90000
00
0@
#95000
b110 M
b110 &
b110 =
b110 Q
10
1@
#100000
00
0@
#105000
b111 M
b111 &
b111 =
b111 Q
10
1@
#110000
00
0@
#115000
b1000 M
b1000 &
b1000 =
b1000 Q
10
1@
#120000
00
0@
#125000
b1001 M
b1001 &
b1001 =
b1001 Q
10
1@
#130000
00
0@
#135000
b0 M
b0 &
b0 =
b1 N
b1 '
b1 >
b1010 Q
10
1@
#140000
00
0@
#145000
b1 M
b1 &
b1 =
b1011 Q
10
1@
#150000
00
0@
#155000
b10 M
b10 &
b10 =
b1100 Q
10
1@
#160000
00
0@
#165000
b11 M
b11 &
b11 =
b1101 Q
10
1@
#170000
00
0@
#175000
b100 M
b100 &
b100 =
b1110 Q
10
1@
#180000
00
0@
#185000
b101 M
b101 &
b101 =
b1111 Q
10
1@
#190000
00
0@
#195000
b110 M
b110 &
b110 =
b10000 Q
10
1@
#200000
00
0@
#205000
b111 M
b111 &
b111 =
b10001 Q
10
1@
#210000
00
0@
#215000
b1000 M
b1000 &
b1000 =
b10010 Q
10
1@
#220000
00
0@
#225000
b1001 M
b1001 &
b1001 =
b10011 Q
10
1@
#230000
00
0@
#235000
b0 M
b0 &
b0 =
b10 N
b10 '
b10 >
b10100 Q
10
1@
#240000
00
0@
#245000
b1 M
b1 &
b1 =
b10101 Q
10
1@
#250000
00
0@
#255000
b10 M
b10 &
b10 =
b10110 Q
10
1@
#260000
00
0@
#265000
b11 M
b11 &
b11 =
b10111 Q
10
1@
#270000
00
0@
#275000
b100 M
b100 &
b100 =
b11000 Q
10
1@
#280000
00
0@
#285000
b101 M
b101 &
b101 =
b11001 Q
10
1@
#290000
00
0@
#295000
b110 M
b110 &
b110 =
b11010 Q
10
1@
#300000
00
0@
#305000
b111 M
b111 &
b111 =
b11011 Q
10
1@
#310000
00
0@
#315000
b1000 M
b1000 &
b1000 =
b11100 Q
10
1@
#320000
00
0@
#325000
b1001 M
b1001 &
b1001 =
b11101 Q
10
1@
#330000
00
0@
#335000
b0 M
b0 &
b0 =
b11 N
b11 '
b11 >
b11110 Q
10
1@
#340000
00
0@
#345000
b1 M
b1 &
b1 =
b11111 Q
10
1@
#350000
00
0@
#355000
b10 M
b10 &
b10 =
b100000 Q
10
1@
#360000
00
0@
#365000
b11 M
b11 &
b11 =
b100001 Q
10
1@
#370000
00
0@
#375000
b100 M
b100 &
b100 =
b100010 Q
10
1@
#380000
00
0@
#385000
b101 M
b101 &
b101 =
b100011 Q
10
1@
#390000
00
0@
#395000
b110 M
b110 &
b110 =
b100100 Q
10
1@
#400000
00
0@
#405000
b111 M
b111 &
b111 =
b100101 Q
10
1@
#410000
00
0@
#415000
b1000 M
b1000 &
b1000 =
b100110 Q
10
1@
#420000
00
0@
#425000
b1001 M
b1001 &
b1001 =
b100111 Q
10
1@
#430000
00
0@
#435000
b0 M
b0 &
b0 =
b100 N
b100 '
b100 >
b101000 Q
10
1@
#440000
00
0@
#445000
b1 M
b1 &
b1 =
b101001 Q
10
1@
#450000
00
0@
#455000
b10 M
b10 &
b10 =
b101010 Q
10
1@
#460000
00
0@
#465000
b11 M
b11 &
b11 =
b101011 Q
10
1@
#470000
00
0@
#475000
b100 M
b100 &
b100 =
b101100 Q
10
1@
#480000
00
0@
#485000
b101 M
b101 &
b101 =
b101101 Q
10
1@
#490000
00
0@
#495000
b110 M
b110 &
b110 =
b101110 Q
10
1@
#500000
00
0@
#505000
b111 M
b111 &
b111 =
b101111 Q
10
1@
#510000
00
0@
#515000
b1000 M
b1000 &
b1000 =
b110000 Q
10
1@
#520000
00
0@
#525000
b1001 M
b1001 &
b1001 =
b110001 Q
10
1@
#530000
00
0@
#535000
b0 M
b0 &
b0 =
b101 N
b101 '
b101 >
b110010 Q
10
1@
#540000
00
0@
#545000
b1 M
b1 &
b1 =
b110011 Q
10
1@
#550000
00
0@
#555000
b10 M
b10 &
b10 =
b110100 Q
10
1@
#560000
00
0@
#565000
b11 M
b11 &
b11 =
b110101 Q
10
1@
#570000
00
0@
#575000
b100 M
b100 &
b100 =
b110110 Q
10
1@
#580000
00
0@
#585000
b101 M
b101 &
b101 =
b110111 Q
10
1@
#590000
00
0@
#595000
b110 M
b110 &
b110 =
b111000 Q
10
1@
#600000
00
0@
#605000
b111 M
b111 &
b111 =
b111001 Q
10
1@
#610000
00
0@
#615000
b1000 M
b1000 &
b1000 =
b111010 Q
10
1@
#620000
00
0@
#625000
b1001 M
b1001 &
b1001 =
b111011 Q
10
1@
#630000
00
0@
#635000
b0 M
b0 &
b0 =
b110 N
b110 '
b110 >
b111100 Q
10
1@
#640000
00
0@
#645000
b0 N
b0 '
b0 >
b1001 K
b1001 $
b1001 ;
b111011 P
b0 Q
10
1@
#650000
00
0@
#655000
b1 M
b1 &
b1 =
b1 Q
1B
1!
10
1@
#660000
00
0@
#665000
b10 M
b10 &
b10 =
b10 Q
10
1@
#670000
00
0@
#675000
b11 M
b11 &
b11 =
b11 Q
0B
0!
10
1@
1/
1?
#680000
00
0@
#685000
b100 M
b100 &
b100 =
b100 Q
10
1@
0/
0?
#690000
00
0@
#695000
b101 M
b101 &
b101 =
b101 Q
10
1@
#700000
00
0@
#705000
b110 M
b110 &
b110 =
b110 Q
10
1@
#710000
00
0@
#715000
b111 M
b111 &
b111 =
b111 Q
10
1@
#720000
00
0@
#725000
b1000 M
b1000 &
b1000 =
b1000 Q
10
1@
#730000
00
0@
#735000
b1001 M
b1001 &
b1001 =
b1001 Q
10
1@
